cshell.py
cshell-1.5.1.dist-info/LICENSE
cshell-1.5.1.dist-info/METADATA
cshell-1.5.1.dist-info/WHEEL
cshell-1.5.1.dist-info/entry_points.txt
cshell-1.5.1.dist-info/top_level.txt
cshell-1.5.1.dist-info/RECORD
